{"how_to_access.md":"C-m8wt8l","network_websocket_index.md":"Cf2gnkpO","other_cors_index.md":"DKDgSCRp","api-examples.md":"BAn5Urs4","readme.md":"C2r6rHzh","buildtools_gulp_index.md":"CGZUhp-u","other_monorepo_index.md":"LMN6u8XR","browser_browser_index.md":"BgrkE_Gy","network_http2_index.md":"CFxIJLns","basics_css_index.md":"D6yVVYYX","interviewkquestions_interviewkq_index.md":"DDZjwZ_F","buildtools_vite_index.md":"CrTxBC77","other_bigfileupload_index.md":"CqKoBgg1","basics_typescript_index.md":"Cd6vh-NN","other_nest_index.md":"B3IrjYJA","network_fetch_index.md":"Dca4NicW","other_cicd_index.md":"D29muyr4","frameworks_react_index.md":"DqPv6Lal","index.md":"CuruufvN","network_http_index.md":"D4zoW19z","network_sse_index.md":"C6KMKSOq","other_tracker_index.md":"BwrHlmbJ","network_ajax_index.md":"mBlcHjzA","buildtools_rollup_index.md":"B6FO-qW3","basics_javascript_index.md":"ClzOvDLh","basics_html_index.md":"Cnt5G1NJ","buildtools_webpack_index.md":"hKqTukqs","markdown-examples.md":"Bo9h1HeP","frameworks_vue_index.md":"JEKXhld4"}
